Workbook

Sheet orders_raw
A1: order_id | B1: date | C1: sku | D1: units | E1: sale_price | F1: amazon_fee_per_unit | H1: revenue_calculation
A2: BZP-001 | B2: 45990 | C2: SPICE-2T | D2: 1 | E2: 18.99 | F2: 10.39 | H2: =D2*E2 -> 18.99
A3: BZP-002 | B3: 45991 | C3: SPICE-3T | D3: 1 | E3: 39.99 | F3: 14.71 | H3: =D3*E3 -> 39.99
A4: BZP-003 | B4: 45992 | C4: SPICE-2T | D4: 1 | E4: 18.99 | F4: 10.39 | H4: =D4*E4 -> 18.99
A5: BZP-004 | B5: 45993 | C5: SPICE-2T | D5: 1 | E5: 18.99 | F5: 10.39 | H5: =D5*E5 -> 18.99
A6: BZP-005 | B6: 45994 | C6: SPICE-2T | D6: 1 | E6: 18.99 | F6: 10.39 | H6: =D6*E6 -> 18.99
A7: BZP-006 | B7: 45995 | C7: SPICE-2T | D7: 1 | E7: 18.99 | F7: 10.39 | H7: =D7*E7 -> 18.99
A8: BZP-007 | B8: 45996 | C8: SPICE-2T | D8: 1 | E8: 18.99 | F8: 10.39 | H8: =D8*E8 -> 18.99
A9: BZP-008 | B9: 45997 | C9: SPICE-2T | D9: 1 | E9: 18.99 | F9: 10.39 | H9: =D9*E9 -> 18.99
A10: BZP-009 | B10: 45998 | C10: SPICE-2T | D10: 1 | E10: 18.99 | F10: 10.39 | H10: =D10*E10 -> 18.99
A11: BZP-010 | B11: 45999 | C11: SPICE-2T | D11: 1 | E11: 18.99 | F11: 10.39 | H11: =D11*E11 -> 18.99
A12: BZP-011 | B12: 46000 | C12: SPICE-2T | D12: 1 | E12: 18.99 | F12: 10.39 | H12: =D12*E12 -> 18.99
A13: BZP-012 | B13: 46001 | C13: SPICE-2T | D13: 1 | E13: 18.99 | F13: 10.39 | H13: =D13*E13 -> 18.99
... A30: BZP-029 | B30: 46018 | C30: SPICE-3T | D30: 1 | E30: 39.99 | F30: 14.71 | H30: =D30*E30 -> 39.99

Sheet product_costs 
A1: sku | B1: supplier_cost | C1: shipping_to_amazon | D1: packaging_cost | E1: landed_unit_cost
A2: SPICE-2T | B2: 3.75 | C2: 1.12 | D2: 1 | E2: 5.87 | F2: =LEN(A2) -> 8
A3: SPICE-3T | B3: 7.71 | C3: 1.5 | D3: 1 | E3: 10.21

Sheet fee_lookup
A1: fee_type | B1: fee_method | C1: fee_value | D1: applies_to | E1: notes
A2: Referral Fee | B2: Percentage | C2: 0.15 | D2: Kitchen Category | E2: Standard Amazon referral fee for Kitchen products
A3: FBA Fulfillment Fee | B3: Fixed | C3: 4.2 | D3: SPICE-2T | E3: Estimated fulfillment fee based on size and weight (2-tier)
A4: FBA Fulfillment Fee | B4: Fixed | C4: 7.33 | D4: SPICE-3T | E4: Estimated fulfillment fee from Helium 10 calculator (3-tier)
A5: Storage Fee | B5: Fixed | C5: 0.1 | D5: All | E5: Average non-peak monthly storage fee per unit

Sheet processed_orders
A1: order_id | B1: date | C1: sku | D1: units | E1: sale_price | F1: revenue | G1: supplier_cost_per_unit | H1: shipping_cost_per_unit | I1: packaging_cost_per_unit | J1: landed_unit_cost | K1: referral_fee | L1: fulfillment_fee | M1: storage_fee | N1: amazon_fee_total | O1: total_cost | P1: net_profit | Q1: profit_margin
A2: BZP-001 | B2: 45990 | C2: SPICE-2T | D2: 1 | E2: 18.99 | F2: =D2*E2 -> 18.99 | G2: =_xlfn.XLOOKUP(processed_orders!C2, 'product_costs '!$A$2:$A$3, 'product_costs '!$B$2:$B$3) -> 3.75 | H2: =_xlfn.XLOOKUP(processed_orders!C2, 'product_costs '!$A$2:$A$3, 'product_costs '!$C$2:$C$3) -> 1.12 | I2: =_xlfn.XLOOKUP(C2, 'product_costs '!$A$2:$A$3, 'product_costs '!$D$2:$D$3) -> 1 | J2: =_xlfn.XLOOKUP(processed_orders!C2, 'product_costs '!$A$2:$A$3, 'product_costs '!$E$2:$E$3) -> 5.87 | K2: =E2*_xlfn.XLOOKUP("Referral Fee", fee_lookup!A:A, fee_lookup!C:C) -> 2.8485 | L2: =_xlfn.XLOOKUP(C2, fee_lookup!D:D, fee_lookup!C:C) -> 4.2 | M2: =fee_lookup!$C$5 -> 0.1 | N2: =K2+L2+M2 -> 7.1485 | O2: =J2+N2 -> 13.0185 | P2: =F2-O2 -> 5.9715 | Q2: =P2/F2 -> 0.31445498
A3: BZP-002 | B3: 45991 | C3: SPICE-3T | D3: 1 | E3: 39.99 | F3: =D3*E3 -> 39.99 | G3: =_xlfn.XLOOKUP(processed_orders!C3, 'product_costs '!$A$2:$A$3, 'product_costs '!$B$2:$B$3) -> 7.71 | H3: =_xlfn.XLOOKUP(processed_orders!C3, 'product_costs '!$A$2:$A$3, 'product_costs '!$C$2:$C$3) -> 1.5 | I3: =_xlfn.XLOOKUP(C3, 'product_costs '!$A$2:$A$3, 'product_costs '!$D$2:$D$3) -> 1 | J3: =_xlfn.XLOOKUP(processed_orders!C3, 'product_costs '!$A$2:$A$3, 'product_costs '!$E$2:$E$3) -> 10.21 | K3: =E3*_xlfn.XLOOKUP("Referral Fee", fee_lookup!A:A, fee_lookup!C:C) -> 5.9985 | L3: =_xlfn.XLOOKUP(C3, fee_lookup!D:D, fee_lookup!C:C) -> 7.33 | M3: =fee_lookup!$C$5 -> 0.1 | N3: =K3+L3+M3 -> 13.4285 | O3: =J3+N3 -> 23.6385 | P3: =F3-O3 -> 16.3515 | Q3: =P3/F3 -> 0.40888972
A4: BZP-003 | B4: 45992 | C4: SPICE-2T | D4: 1 | E4: 18.99 | F4: =D4*E4 -> 18.99 | G4: =_xlfn.XLOOKUP(processed_orders!C4, 'product_costs '!$A$2:$A$3, 'product_costs '!$B$2:$B$3) -> 3.75 | H4: =_xlfn.XLOOKUP(processed_orders!C4, 'product_costs '!$A$2:$A$3, 'product_costs '!$C$2:$C$3) -> 1.12 | I4: =_xlfn.XLOOKUP(C4, 'product_costs '!$A$2:$A$3, 'product_costs '!$D$2:$D$3) -> 1 | J4: =_xlfn.XLOOKUP(processed_orders!C4, 'product_costs '!$A$2:$A$3, 'product_costs '!$E$2:$E$3) -> 5.87 | K4: =E4*_xlfn.XLOOKUP("Referral Fee", fee_lookup!A:A, fee_lookup!C:C) -> 2.8485 | L4: =_xlfn.XLOOKUP(C4, fee_lookup!D:D, fee_lookup!C:C) -> 4.2 | M4: =fee_lookup!$C$5 -> 0.1 | N4: =K4+L4+M4 -> 7.1485 | O4: =J4+N4 -> 13.0185 | P4: =F4-O4 -> 5.9715 | Q4: =P4/F4 -> 0.31445498
A5: BZP-004 | B5: 45993 | C5: SPICE-2T | D5: 1 | E5: 18.99 | F5: =D5*E5 -> 18.99 | G5: =_xlfn.XLOOKUP(processed_orders!C5, 'product_costs '!$A$2:$A$3, 'product_costs '!$B$2:$B$3) -> 3.75 | H5: =_xlfn.XLOOKUP(processed_orders!C5, 'product_costs '!$A$2:$A$3, 'product_costs '!$C$2:$C$3) -> 1.12 | I5: =_xlfn.XLOOKUP(C5, 'product_costs '!$A$2:$A$3, 'product_costs '!$D$2:$D$3) -> 1 | J5: =_xlfn.XLOOKUP(processed_orders!C5, 'product_costs '!$A$2:$A$3, 'product_costs '!$E$2:$E$3) -> 5.87 | K5: =E5*_xlfn.XLOOKUP("Referral Fee", fee_lookup!A:A, fee_lookup!C:C) -> 2.8485 | L5: =_xlfn.XLOOKUP(C5, fee_lookup!D:D, fee_lookup!C:C) -> 4.2 | M5: =fee_lookup!$C$5 -> 0.1 | N5: =K5+L5+M5 -> 7.1485 | O5: =J5+N5 -> 13.0185 | P5: =F5-O5 -> 5.9715 | Q5: =P5/F5 -> 0.31445498
A6: BZP-005 | B6: 45994 | C6: SPICE-2T | D6: 1 | E6: 18.99 | F6: =D6*E6 -> 18.99 | G6: =_xlfn.XLOOKUP(processed_orders!C6, 'product_costs '!$A$2:$A$3, 'product_costs '!$B$2:$B$3) -> 3.75 | H6: =_xlfn.XLOOKUP(processed_orders!C6, 'product_costs '!$A$2:$A$3, 'product_costs '!$C$2:$C$3) -> 1.12 | I6: =_xlfn.XLOOKUP(C6, 'product_costs '!$A$2:$A$3, 'product_costs '!$D$2:$D$3) -> 1 | J6: =_xlfn.XLOOKUP(processed_orders!C6, 'product_costs '!$A$2:$A$3, 'product_costs '!$E$2:$E$3) -> 5.87 | K6: =E6*_xlfn.XLOOKUP("Referral Fee", fee_lookup!A:A, fee_lookup!C:C) -> 2.8485 | L6: =_xlfn.XLOOKUP(C6, fee_lookup!D:D, fee_lookup!C:C) -> 4.2 | M6: =fee_lookup!$C$5 -> 0.1 | N6: =K6+L6+M6 -> 7.1485 | O6: =J6+N6 -> 13.0185 | P6: =F6-O6 -> 5.9715 | Q6: =P6/F6 -> 0.31445498
A7: BZP-006 | B7: 45995 | C7: SPICE-2T | D7: 1 | E7: 18.99 | F7: =D7*E7 -> 18.99 | G7: =_xlfn.XLOOKUP(processed_orders!C7, 'product_costs '!$A$2:$A$3, 'product_costs '!$B$2:$B$3) -> 3.75 | H7: =_xlfn.XLOOKUP(processed_orders!C7, 'product_costs '!$A$2:$A$3, 'product_costs '!$C$2:$C$3) -> 1.12 | I7: =_xlfn.XLOOKUP(C7, 'product_costs '!$A$2:$A$3, 'product_costs '!$D$2:$D$3) -> 1 | J7: =_xlfn.XLOOKUP(processed_orders!C7, 'product_costs '!$A$2:$A$3, 'product_costs '!$E$2:$E$3) -> 5.87 | K7: =E7*_xlfn.XLOOKUP("Referral Fee", fee_lookup!A:A, fee_lookup!C:C) -> 2.8485 | L7: =_xlfn.XLOOKUP(C7, fee_lookup!D:D, fee_lookup!C:C) -> 4.2 | M7: =fee_lookup!$C$5 -> 0.1 | N7: =K7+L7+M7 -> 7.1485 | O7: =J7+N7 -> 13.0185 | P7: =F7-O7 -> 5.9715 | Q7: =P7/F7 -> 0.31445498
A8: BZP-007 | B8: 45996 | C8: SPICE-2T | D8: 1 | E8: 18.99 | F8: =D8*E8 -> 18.99 | G8: =_xlfn.XLOOKUP(processed_orders!C8, 'product_costs '!$A$2:$A$3, 'product_costs '!$B$2:$B$3) -> 3.75 | H8: =_xlfn.XLOOKUP(processed_orders!C8, 'product_costs '!$A$2:$A$3, 'product_costs '!$C$2:$C$3) -> 1.12 | I8: =_xlfn.XLOOKUP(C8, 'product_costs '!$A$2:$A$3, 'product_costs '!$D$2:$D$3) -> 1 | J8: =_xlfn.XLOOKUP(processed_orders!C8, 'product_costs '!$A$2:$A$3, 'product_costs '!$E$2:$E$3) -> 5.87 | K8: =E8*_xlfn.XLOOKUP("Referral Fee", fee_lookup!A:A, fee_lookup!C:C) -> 2.8485 | L8: =_xlfn.XLOOKUP(C8, fee_lookup!D:D, fee_lookup!C:C) -> 4.2 | M8: =fee_lookup!$C$5 -> 0.1 | N8: =K8+L8+M8 -> 7.1485 | O8: =J8+N8 -> 13.0185 | P8: =F8-O8 -> 5.9715 | Q8: =P8/F8 -> 0.31445498
A9: BZP-008 | B9: 45997 | C9: SPICE-2T | D9: 1 | E9: 18.99 | F9: =D9*E9 -> 18.99 | G9: =_xlfn.XLOOKUP(processed_orders!C9, 'product_costs '!$A$2:$A$3, 'product_costs '!$B$2:$B$3) -> 3.75 | H9: =_xlfn.XLOOKUP(processed_orders!C9, 'product_costs '!$A$2:$A$3, 'product_costs '!$C$2:$C$3) -> 1.12 | I9: =_xlfn.XLOOKUP(C9, 'product_costs '!$A$2:$A$3, 'product_costs '!$D$2:$D$3) -> 1 | J9: =_xlfn.XLOOKUP(processed_orders!C9, 'product_costs '!$A$2:$A$3, 'product_costs '!$E$2:$E$3) -> 5.87 | K9: =E9*_xlfn.XLOOKUP("Referral Fee", fee_lookup!A:A, fee_lookup!C:C) -> 2.8485 | L9: =_xlfn.XLOOKUP(C9, fee_lookup!D:D, fee_lookup!C:C) -> 4.2 | M9: =fee_lookup!$C$5 -> 0.1 | N9: =K9+L9+M9 -> 7.1485 | O9: =J9+N9 -> 13.0185 | P9: =F9-O9 -> 5.9715 | Q9: =P9/F9 -> 0.31445498
A10: BZP-009 | B10: 45998 | C10: SPICE-2T | D10: 1 | E10: 18.99 | F10: =D10*E10 -> 18.99 | G10: =_xlfn.XLOOKUP(processed_orders!C10, 'product_costs '!$A$2:$A$3, 'product_costs '!$B$2:$B$3) -> 3.75 | H10: =_xlfn.XLOOKUP(processed_orders!C10, 'product_costs '!$A$2:$A$3, 'product_costs '!$C$2:$C$3) -> 1.12 | I10: =_xlfn.XLOOKUP(C10, 'product_costs '!$A$2:$A$3, 'product_costs '!$D$2:$D$3) -> 1 | J10: =_xlfn.XLOOKUP(processed_orders!C10, 'product_costs '!$A$2:$A$3, 'product_costs '!$E$2:$E$3) -> 5.87 | K10: =E10*_xlfn.XLOOKUP("Referral Fee", fee_lookup!A:A, fee_lookup!C:C) -> 2.8485 | L10: =_xlfn.XLOOKUP(C10, fee_lookup!D:D, fee_lookup!C:C) -> 4.2 | M10: =fee_lookup!$C$5 -> 0.1 | N10: =K10+L10+M10 -> 7.1485 | O10: =J10+N10 -> 13.0185 | P10: =F10-O10 -> 5.9715 | Q10: =P10/F10 -> 0.31445498
A11: BZP-010 | B11: 45999 | C11: SPICE-2T | D11: 1 | E11: 18.99 | F11: =D11*E11 -> 18.99 | G11: =_xlfn.XLOOKUP(processed_orders!C11, 'product_costs '!$A$2:$A$3, 'product_costs '!$B$2:$B$3) -> 3.75 | H11: =_xlfn.XLOOKUP(processed_orders!C11, 'product_costs '!$A$2:$A$3, 'product_costs '!$C$2:$C$3) -> 1.12 | I11: =_xlfn.XLOOKUP(C11, 'product_costs '!$A$2:$A$3, 'product_costs '!$D$2:$D$3) -> 1 | J11: =_xlfn.XLOOKUP(processed_orders!C11, 'product_costs '!$A$2:$A$3, 'product_costs '!$E$2:$E$3) -> 5.87 | K11: =E11*_xlfn.XLOOKUP("Referral Fee", fee_lookup!A:A, fee_lookup!C:C) -> 2.8485 | L11: =_xlfn.XLOOKUP(C11, fee_lookup!D:D, fee_lookup!C:C) -> 4.2 | M11: =fee_lookup!$C$5 -> 0.1 | N11: =K11+L11+M11 -> 7.1485 | O11: =J11+N11 -> 13.0185 | P11: =F11-O11 -> 5.9715 | Q11: =P11/F11 -> 0.31445498
A12: BZP-011 | B12: 46000 | C12: SPICE-2T | D12: 1 | E12: 18.99 | F12: =D12*E12 -> 18.99 | G12: =_xlfn.XLOOKUP(processed_orders!C12, 'product_costs '!$A$2:$A$3, 'product_costs '!$B$2:$B$3) -> 3.75 | H12: =_xlfn.XLOOKUP(processed_orders!C12, 'product_costs '!$A$2:$A$3, 'product_costs '!$C$2:$C$3) -> 1.12 | I12: =_xlfn.XLOOKUP(C12, 'product_costs '!$A$2:$A$3, 'product_costs '!$D$2:$D$3) -> 1 | J12: =_xlfn.XLOOKUP(processed_orders!C12, 'product_costs '!$A$2:$A$3, 'product_costs '!$E$2:$E$3) -> 5.87 | K12: =E12*_xlfn.XLOOKUP("Referral Fee", fee_lookup!A:A, fee_lookup!C:C) -> 2.8485 | L12: =_xlfn.XLOOKUP(C12, fee_lookup!D:D, fee_lookup!C:C) -> 4.2 | M12: =fee_lookup!$C$5 -> 0.1 | N12: =K12+L12+M12 -> 7.1485 | O12: =J12+N12 -> 13.0185 | P12: =F12-O12 -> 5.9715 | Q12: =P12/F12 -> 0.31445498
A13: BZP-012 | B13: 46001 | C13: SPICE-2T | D13: 1 | E13: 18.99 | F13: =D13*E13 -> 18.99 | G13: =_xlfn.XLOOKUP(processed_orders!C13, 'product_costs '!$A$2:$A$3, 'product_costs '!$B$2:$B$3) -> 3.75 | H13: =_xlfn.XLOOKUP(processed_orders!C13, 'product_costs '!$A$2:$A$3, 'product_costs '!$C$2:$C$3) -> 1.12 | I13: =_xlfn.XLOOKUP(C13, 'product_costs '!$A$2:$A$3, 'product_costs '!$D$2:$D$3) -> 1 | J13: =_xlfn.XLOOKUP(processed_orders!C13, 'product_costs '!$A$2:$A$3, 'product_costs '!$E$2:$E$3) -> 5.87 | K13: =E13*_xlfn.XLOOKUP("Referral Fee", fee_lookup!A:A, fee_lookup!C:C) -> 2.8485 | L13: =_xlfn.XLOOKUP(C13, fee_lookup!D:D, fee_lookup!C:C) -> 4.2 | M13: =fee_lookup!$C$5 -> 0.1 | N13: =K13+L13+M13 -> 7.1485 | O13: =J13+N13 -> 13.0185 | P13: =F13-O13 -> 5.9715 | Q13: =P13/F13 -> 0.31445498
... A30: BZP-029 | B30: 46018 | C30: SPICE-3T | D30: 1 | E30: 39.99 | F30: =D30*E30 -> 39.99 | G30: =_xlfn.XLOOKUP(processed_orders!C30, 'product_costs '!$A$2:$A$3, 'product_costs '!$B$2:$B$3) -> 7.71 | H30: =_xlfn.XLOOKUP(processed_orders!C30, 'product_costs '!$A$2:$A$3, 'product_costs '!$C$2:$C$3) -> 1.5 | I30: =_xlfn.XLOOKUP(C30, 'product_costs '!$A$2:$A$3, 'product_costs '!$D$2:$D$3) -> 1 | J30: =_xlfn.XLOOKUP(processed_orders!C30, 'product_costs '!$A$2:$A$3, 'product_costs '!$E$2:$E$3) -> 10.21 | K30: =E30*_xlfn.XLOOKUP("Referral Fee", fee_lookup!A:A, fee_lookup!C:C) -> 5.9985 | L30: =_xlfn.XLOOKUP(C30, fee_lookup!D:D, fee_lookup!C:C) -> 7.33 | M30: =fee_lookup!$C$5 -> 0.1 | N30: =K30+L30+M30 -> 13.4285 | O30: =J30+N30 -> 23.6385 | P30: =F30-O30 -> 16.3515 | Q30: =P30/F30 -> 0.40888972

Sheet pivot_sku_profitabilty
A3: Row Labels | B3: Sum of revenue | C3: Sum of total_cost | D3: Sum of net_profit | E3: Average of profit_margin
A4: SPICE-2T | B4: 284.85 | C4: 195.2775 | D4: 89.5725 | E4: 0.31445498
A5: SPICE-3T | B5: 599.85 | C5: 330.939 | D5: 268.911 | E5: 0.4300008
A6: Grand Total | B6: 884.7 | C6: 526.2165 | D6: 358.4835 | E6: 0.37023572

Sheet reconciliation_checks
A3: revenue_order_raw | B3: =SUM(orders_raw!H2:H1000) -> 884.7
A4: revenue_processed_orders | B4: =SUM(tbl_processed[revenue]) -> 884.7
A5: difference | B5: =B4-B3 -> 0
A6: status | B6: =IF(ABS(B5)<0.01,"PASS","FAIL") -> PASS

Sheet forecasting_and_sensitivity 
A1: sku | B1: average_daily_unit | C1: average_daily_net_profit | D1: base_30d_units | E1: base_30d_net_profit | F1: net_profit_downside_10pct | G1: net_profit_upside_10pct
A2: SPICE-2T | B2: =AVERAGEIF(processed_orders!C:C, "SPICE-2T", processed_orders!D:D) -> 1 | C2: =AVERAGEIF(processed_orders!C:C, "SPICE-2T", processed_orders!P:P) -> 5.9715 | D2: =B2 * 30 -> 30 | E2: =C2 * 30 -> 179.145 | F2: =E2*0.9 -> 161.2305 | G2: =E2*1.1 -> 197.0595
A3: SPICE-3T | B3: =AVERAGEIF(processed_orders!C:C, "SPICE-3T", processed_orders!D:D) -> 1.0714286 | C3: =AVERAGEIF(processed_orders!C:C, "SPICE-3T", processed_orders!P:P) -> 19.207929 | D3: =B3 * 30 -> 32.142857 | E3: =C3 * 30 -> 576.23786 | F3: =E3*0.9 -> 518.61407 | G3: =E3*1.1 -> 633.86164
A4: =TRIM(CLEAN(J2))
